pycodedock/__init__.py
pycodedock/correct_code.py
pycodedock/dock.py
pycodedock/docker.py
pycodedock/error_code.py
pycodedock/tle_code.py
pycodedock/wrong_code.py
pycodedock-0.0.3.dist-info/LICENSE
pycodedock-0.0.3.dist-info/METADATA
pycodedock-0.0.3.dist-info/WHEEL
pycodedock-0.0.3.dist-info/top_level.txt
pycodedock-0.0.3.dist-info/RECORD
